{
  "game": "Geometry Dash",
  "gameID": "GeometryDash",
  "platform": "PC",
  "executable": "GeometryDash.exe",
  "port": 33941,
  "protocol": "tcp",
  "modRequired": true,
  "modVersion": "1.1.2",
  "modPath": "{gamePath}\\..\\geode\\mods\\",
  "modUrl": "https://files.catbox.moe/we3lzw.zip",
  "modFramework": "Geode SDK",
  "uninstaller": "GeodeUninstaller.exe",
  "steam": {
    "id": 322170
  },
  "guide": "https://crowdcontrol.live/guides/GeometryDash",
  "description": "Geometry Dash integration via Geode modding framework. Supports GD 2.206.",
  "categories": {
    "Camera": {
      "icon": "📷",
      "color": "#3b82f6"
    },
    "Size": {
      "icon": "📏",
      "color": "#8b5cf6"
    },
    "Color": {
      "icon": "🎨",
      "color": "#ec4899"
    },
    "Controls": {
      "icon": "🎮",
      "color": "#f59e0b"
    },
    "Player": {
      "icon": "👤",
      "color": "#10b981"
    }
  },
  "effects": [
    {
      "id": "zoomin",
      "name": "Close Up Camera",
      "nameTranslations": {
        "es": "Cámara Cercana"
      },
      "category": "Camera",
      "price": 100,
      "duration": 10,
      "description": "Zoom in the camera for close-up view",
      "descriptionTranslations": {
        "es": "Acerca la cámara para una vista cercana"
      }
    },
    {
      "id": "zoomout",
      "name": "Far Camera",
      "nameTranslations": {
        "es": "Cámara Lejana"
      },
      "category": "Camera",
      "price": 25,
      "duration": 10,
      "description": "Zoom out the camera",
      "descriptionTranslations": {
        "es": "Aleja la cámara"
      }
    },
    {
      "id": "zoomout2",
      "name": "Ultra Far Camera",
      "nameTranslations": {
        "es": "Cámara Ultra Lejana"
      },
      "category": "Camera",
      "price": 100,
      "duration": 10,
      "description": "Zoom out the camera to the maximum",
      "descriptionTranslations": {
        "es": "Aleja la cámara al máximo"
      }
    },
    {
      "id": "rotate",
      "name": "Skew Camera",
      "nameTranslations": {
        "es": "Cámara Inclinada"
      },
      "category": "Camera",
      "price": 50,
      "duration": 10,
      "description": "Skew the camera view",
      "descriptionTranslations": {
        "es": "Inclina la vista de la cámara"
      }
    },
    {
      "id": "rotate2",
      "name": "Strong Skew Camera",
      "nameTranslations": {
        "es": "Cámara Muy Inclinada"
      },
      "category": "Camera",
      "price": 300,
      "duration": 10,
      "description": "Strongly skew the camera view",
      "descriptionTranslations": {
        "es": "Inclina mucho la vista de la cámara"
      }
    },
    {
      "id": "rotate3",
      "name": "Tilt Camera",
      "nameTranslations": {
        "es": "Cámara Ladeada"
      },
      "category": "Camera",
      "price": 50,
      "duration": 10,
      "description": "Tilt the camera",
      "descriptionTranslations": {
        "es": "Ladea la cámara"
      }
    },
    {
      "id": "rotate4",
      "name": "Strong Tilt Camera",
      "nameTranslations": {
        "es": "Cámara Muy Ladeada"
      },
      "category": "Camera",
      "price": 300,
      "duration": 10,
      "description": "Strongly tilt the camera",
      "descriptionTranslations": {
        "es": "Ladea mucho la cámara"
      }
    },
    {
      "id": "rotate5",
      "name": "Rotate Camera",
      "nameTranslations": {
        "es": "Rotar Cámara"
      },
      "category": "Camera",
      "price": 25,
      "duration": 10,
      "description": "Rotate the camera view",
      "descriptionTranslations": {
        "es": "Rota la vista de la cámara"
      }
    },
    {
      "id": "rotate6",
      "name": "Flip Camera",
      "nameTranslations": {
        "es": "Voltear Cámara"
      },
      "category": "Camera",
      "price": 150,
      "duration": 10,
      "description": "Flip the camera 180 degrees",
      "descriptionTranslations": {
        "es": "Voltea la cámara 180 grados"
      }
    },
    {
      "id": "spin",
      "name": "Spin Camera",
      "nameTranslations": {
        "es": "Girar Cámara"
      },
      "category": "Camera",
      "price": 500,
      "duration": 0,
      "description": "Make the camera spin continuously",
      "descriptionTranslations": {
        "es": "Hace que la cámara gire continuamente"
      }
    },
    {
      "id": "invis",
      "name": "Invisible Player",
      "nameTranslations": {
        "es": "Jugador Invisible"
      },
      "category": "Player",
      "price": 50,
      "duration": 10,
      "description": "Make the player invisible",
      "descriptionTranslations": {
        "es": "Hace al jugador invisible"
      }
    },
    {
      "id": "reverse",
      "name": "Reverse Player",
      "nameTranslations": {
        "es": "Jugador al Revés"
      },
      "category": "Player",
      "price": 100,
      "duration": 3,
      "description": "Reverse player direction",
      "descriptionTranslations": {
        "es": "Invierte la dirección del jugador"
      }
    },
    {
      "id": "invert",
      "name": "Invert Controls",
      "nameTranslations": {
        "es": "Invertir Controles"
      },
      "category": "Controls",
      "price": 200,
      "duration": 10,
      "description": "Invert the game controls",
      "descriptionTranslations": {
        "es": "Invierte los controles del juego"
      }
    },
    {
      "id": "giant",
      "name": "Giant Player",
      "nameTranslations": {
        "es": "Jugador Gigante"
      },
      "category": "Size",
      "price": 25,
      "duration": 10,
      "description": "Make the player giant",
      "descriptionTranslations": {
        "es": "Hace al jugador gigante"
      }
    },
    {
      "id": "tiny",
      "name": "Tiny Player",
      "nameTranslations": {
        "es": "Jugador Pequeño"
      },
      "category": "Size",
      "price": 25,
      "duration": 10,
      "description": "Make the player tiny",
      "descriptionTranslations": {
        "es": "Hace al jugador pequeño"
      }
    },
    {
      "id": "red",
      "name": "Red Player",
      "nameTranslations": {
        "es": "Jugador Rojo"
      },
      "category": "Color",
      "price": 10,
      "duration": 0,
      "description": "Change player color to red",
      "descriptionTranslations": {
        "es": "Cambia el color del jugador a rojo"
      }
    },
    {
      "id": "orange",
      "name": "Orange Player",
      "nameTranslations": {
        "es": "Jugador Naranja"
      },
      "category": "Color",
      "price": 10,
      "duration": 0,
      "description": "Change player color to orange",
      "descriptionTranslations": {
        "es": "Cambia el color del jugador a naranja"
      }
    },
    {
      "id": "yellow",
      "name": "Yellow Player",
      "nameTranslations": {
        "es": "Jugador Amarillo"
      },
      "category": "Color",
      "price": 10,
      "duration": 0,
      "description": "Change player color to yellow",
      "descriptionTranslations": {
        "es": "Cambia el color del jugador a amarillo"
      }
    },
    {
      "id": "green",
      "name": "Green Player",
      "nameTranslations": {
        "es": "Jugador Verde"
      },
      "category": "Color",
      "price": 10,
      "duration": 0,
      "description": "Change player color to green",
      "descriptionTranslations": {
        "es": "Cambia el color del jugador a verde"
      }
    },
    {
      "id": "blue",
      "name": "Blue Player",
      "nameTranslations": {
        "es": "Jugador Azul"
      },
      "category": "Color",
      "price": 10,
      "duration": 0,
      "description": "Change player color to blue",
      "descriptionTranslations": {
        "es": "Cambia el color del jugador a azul"
      }
    },
    {
      "id": "purple",
      "name": "Purple Player",
      "nameTranslations": {
        "es": "Jugador Morado"
      },
      "category": "Color",
      "price": 10,
      "duration": 0,
      "description": "Change player color to purple",
      "descriptionTranslations": {
        "es": "Cambia el color del jugador a morado"
      }
    },
    {
      "id": "pink",
      "name": "Pink Player",
      "nameTranslations": {
        "es": "Jugador Rosa"
      },
      "category": "Color",
      "price": 10,
      "duration": 0,
      "description": "Change player color to pink",
      "descriptionTranslations": {
        "es": "Cambia el color del jugador a rosa"
      }
    },
    {
      "id": "white",
      "name": "White Player",
      "nameTranslations": {
        "es": "Jugador Blanco"
      },
      "category": "Color",
      "price": 10,
      "duration": 0,
      "description": "Change player color to white",
      "descriptionTranslations": {
        "es": "Cambia el color del jugador a blanco"
      }
    },
    {
      "id": "black",
      "name": "Black Player",
      "nameTranslations": {
        "es": "Jugador Negro"
      },
      "category": "Color",
      "price": 10,
      "duration": 0,
      "description": "Change player color to black",
      "descriptionTranslations": {
        "es": "Cambia el color del jugador a negro"
      }
    }
  ]
}


