{
  "serverBaseUrl": "https://TU-APP.up.railway.app",
  "localDashboardBaseUrl": "http://127.0.0.1:5123",
  "dashboardKey": "",
  "reconnectDelayMs": 2500,
  "minecraft": {
    "enabled": true,
    "localBridgeHost": "127.0.0.1",
    "localBridgePort": 6135,
    "useRcon": true,
    "rconHost": "127.0.0.1",
    "rconPort": 25575,
    "rconPassword": "REEMPLAZA_CON_TU_PASSWORD_RCON"
  },
  "gta": {
    "enabled": true,
    "localBridgeHost": "127.0.0.1",
    "localBridgePort": 6136
  },
  "chaosmod": {
    "enabled": true,
    "modPath": "C:\\Program Files\\Epic Games\\GTAVEnhanced\\chaosmod",
    "gtaProcessName": "GTA5_Enhanced",
    "preferShortcutTrigger": true,
    "allowMenuFallback": true,
    "shortcutReloadDelayMs": 850,
    "shortcutPostReloadDelayMs": 1400,
    "shortcutKeyDelayMs": 45,
    "menuOpenDelayMs": 220,
    "keyDelayMs": 35
  }
}
